modern_urwid/__about__.py
modern_urwid/__init__.py
modern_urwid/compiler.py
modern_urwid/constants.py
modern_urwid/context.py
modern_urwid/decorators.py
modern_urwid/exceptions.py
modern_urwid/lifecycle/controller.py
modern_urwid/lifecycle/manager.py
modern_urwid/resource/dummies.py
modern_urwid/resource/registry.py
modern_urwid/resource/utils.py
modern_urwid/style/css_parser.py
modern_urwid/style/registry.py
modern_urwid/widgets/builder.py
modern_urwid/widgets/builders.py
modern_urwid/widgets/registry.py
modern_urwid/widgets/size_options.py
modern_urwid/xml/ast.py
modern_urwid/xml/parser.py
modern_urwid-1.1.3.dist-info/METADATA
modern_urwid-1.1.3.dist-info/WHEEL
modern_urwid-1.1.3.dist-info/licenses/LICENSE
modern_urwid-1.1.3.dist-info/RECORD
