Metadata-Version: 2.4
Name: modern-urwid
Version: 1.1.3
Summary: An urwid library for creating TUIs from XML and CSS
Project-URL: Documentation, https://modern-urwid.readthedocs.io/en/latest/
Project-URL: Issues, https://github.com/Jackkillian/modern-urwid/issues
Project-URL: Source, https://github.com/Jackkillian/modern-urwid
Author-email: Jackkillian <jackkillian@tuta.com>
License-Expression: MIT
License-File: LICENSE
Keywords: css,python,styling,tui,urwid,xml
Classifier: Development Status :: 5 - Production/Stable
Classifier: Environment :: Console
Classifier: Intended Audience :: Developers
Classifier: License :: OSI Approved :: MIT License
Classifier: Programming Language :: Python
Classifier: Programming Language :: Python :: 3.9
Classifier: Programming Language :: Python :: 3.10
Classifier: Programming Language :: Python :: 3.11
Classifier: Programming Language :: Python :: 3.12
Classifier: Programming Language :: Python :: Implementation :: CPython
Classifier: Programming Language :: Python :: Implementation :: PyPy
Requires-Python: >=3.9
Requires-Dist: cssselect2
Requires-Dist: dict-hash
Requires-Dist: lxml
Requires-Dist: tinycss2
Requires-Dist: types-lxml
Requires-Dist: typing-extensions
Requires-Dist: urwid
